stache_ai_ocr/__init__.py
stache_ai_ocr/loaders.py
stache_ai_ocr/types.py
stache_ai_ocr-0.1.2.dist-info/METADATA
stache_ai_ocr-0.1.2.dist-info/WHEEL
stache_ai_ocr-0.1.2.dist-info/entry_points.txt
stache_ai_ocr-0.1.2.dist-info/top_level.txt
stache_ai_ocr-0.1.2.dist-info/RECORD
