Metadata-Version: 2.1
Name: stache-ai-ocr
Version: 0.1.2
Summary: OCR support for Stache AI document loaders
Author: Stache Contributors
License: MIT
Project-URL: Homepage, https://github.com/stache-ai/stache-ai
Project-URL: Repository, https://github.com/stache-ai/stache-ai
Keywords: stache,ocr,pdf,document-processing
Classifier: Development Status :: 4 - Beta
Classifier: Intended Audience :: Developers
Classifier: Operating System :: OS Independent
Classifier: Programming Language :: Python :: 3
Classifier: Programming Language :: Python :: 3.10
Classifier: Programming Language :: Python :: 3.11
Classifier: Programming Language :: Python :: 3.12
Requires-Python: >=3.10
Requires-Dist: stache-ai>=0.1.0
Requires-Dist: pdfplumber>=0.10.0
